sqlalchemy_mimer/__init__.py
sqlalchemy_mimer/_version.py
sqlalchemy_mimer/compiler.py
sqlalchemy_mimer/dialect.py
sqlalchemy_mimer/types.py
sqlalchemy_mimer-1.0.2.dist-info/LICENSE.txt
sqlalchemy_mimer-1.0.2.dist-info/METADATA
sqlalchemy_mimer-1.0.2.dist-info/WHEEL
sqlalchemy_mimer-1.0.2.dist-info/entry_points.txt
sqlalchemy_mimer-1.0.2.dist-info/top_level.txt
sqlalchemy_mimer-1.0.2.dist-info/RECORD
