Metadata-Version: 2.2
Name: sqlalchemy-mimer
Version: 1.0.2
Summary: SQLAlchemy dialect for Mimer SQL (via MimerPy/PEP 249)
Author-email: Fredrik Ålund <fredrik.alund@mimer.com>, Mimer Information Technology AB <info@mimer.com>
License: MIT
Project-URL: Homepage, https://github.com/mimersql/sqlalchemy-mimer
Project-URL: Repository, https://github.com/mimersql/sqlalchemy-mimer
Project-URL: Documentation, https://github.com/mimersql/sqlalchemy-mimer#readme
Project-URL: Issues, https://github.com/mimersql/sqlalchemy-mimer/issues
Keywords: sqlalchemy,mimer,mimer sql,database,dialect,dbapi
Classifier: Development Status :: 5 - Production/Stable
Classifier: Intended Audience :: Developers
Classifier: Topic :: Database
Classifier: Programming Language :: Python :: 3
Classifier: Operating System :: OS Independent
Requires-Python: >=3.8
License-File: LICENSE.txt
Requires-Dist: SQLAlchemy>=2.0
Requires-Dist: mimerpy>=1.3.6
